fpu_adder/fpu_add.sv
// Code your design here

//________IEEE Floating Point Adder (Single Precision)________//


/////////////////////////////________Block Diagram________////////////////////////////////////////////////////////////////////////////////////////////



//                        +-------------------+
//          input_a     =>|                   |=> output_sum
//          input_b     =>|                   |
//                        |      adder        |=> adder_output_STB
//      adder_input_STB =>|                   |<= output_module_BUSY
//           adder_BUSY <=|                   |
//                        +--------^-|--------+
//                clk______________| |
//              rst__________________|



/////////////////////////////________Specification________////////////////////////////////////////////////////////////////////////////////////////////

//1. A transaction takes place any time the input STB line (adder_input_STB) is true and the output BUSY line (adder_BUSY) is false.
//2. Adder needs to be careful not to ever lower the output BUSY line (adder_BUSY), unless it is ready to receive data.
//3. The input STB (adder_input_STB) line should be raised any time input data is ready for sending. The data source must not wait for adder BUSY (adder_BUSY) to be false before raising the input STB line (adder_input_STB).
//4. Busy should be IDLE or 0 (adder_BUSY) when full adder is not busy.
//5. Once input STB (adder_input_STB) is raised, the data being transferred cannot be changed until the clock after the transaction takes place.
//6. The Data lines (output_sum) hold the previous valid output any time output STB (adder_output_STB) is false.
//7. At Reset output adder_BUSY=0, output adder_output_STB=0, and output data lines will be in don't care.


/////////////////////////////________Port_____List________/////////////////////////////////////////////////////////////////////////////////////////////


//       +_____________________________________________________________________________________________________________________________________________________+
//       |#Port Name           | #Direction  | #Width   |  #Description                                                                                        |
//       |_____________________|_____________|__________|______________________________________________________________________________________________________|
//       |  input_a            |     input   |     32   |  Input operand a                                                                                     |
//       |  input_b            |     input   |     32   |  Input operand b                                                                                     |
//       |  adder_input_STB    |     input   |     1    |  Input valid signal, indicates input is valid                                                        |
//       |  adder_BUSY         |     output  |     1    |  Output busy signal, indicates adder is busy and cannot process next input until current one is done |
//       |  clk                |     input   |     1    |  Clock sample                                                                                        |
//       |  rst                |     input   |     1    |  Active high reset                                                                                   |
//       |  output_sum         |     output  |     32   |  Output summation result                                                                             |
//       |  adder_output_STB   |     output  |     1    |  Output valid signal, indicates output is valid                                                      |
//       |  output_module_BUSY |     input   |     1    |  Input busy signal, indicates output module is busy, cannot take next input                          |
//       |_____________________|_____________|__________|______________________________________________________________________________________________________|

module adder(
        input_a,
        input_b,
		adder_input_STB,
		adder_BUSY,
        clk,
        rst,
		output_sum,
        adder_output_STB,
        output_module_BUSY
		);

  input     clk;
  input     rst;

  input     [31:0] input_a;

  input     [31:0] input_b;
  
  input     adder_input_STB;
  output    adder_BUSY;
  
  output    [31:0] output_sum;
  
  output    adder_output_STB;
  input     output_module_BUSY;

  //Intermediate registers
  reg       adder_output_STB_reg;
  reg       [31:0] output_sum_reg;
  reg       adder_BUSY_reg;

  reg       [3:0] state;
  
  parameter get_a_and_b   = 4'd0,
            unpack        = 4'd1,
            special_cases = 4'd2,
            align         = 4'd3,
            add_0         = 4'd4,
            add_1         = 4'd5,
            normalise_1   = 4'd6,
            normalise_2   = 4'd7,
            round         = 4'd8,
            pack          = 4'd9,
            put_z         = 4'd10;

  reg       [31:0] a, b, z;
  reg       [26:0] a_m, b_m;
  reg       [23:0] z_m;
  reg       [9:0] a_e, b_e, z_e;
  reg       a_s, b_s, z_s;
  reg       guard, round_bit, sticky;
  reg       [27:0] sum;

  always @(posedge clk)
  begin

    case(state)

      get_a_and_b: //Initial state wait for valid inputs and make BUSY = 0 because it has finished previous operation 
      begin
        adder_BUSY_reg <= 0;
        if (!(adder_BUSY_reg) && adder_input_STB) begin  //Once it gets valid input take that input and start processing.
          a <= input_a;
		  b <= input_b;
          adder_BUSY_reg <= 1; //Turn the BUSY signal on, BUSY = 1 because now it will be busy processing latched inputs and can no more take inputs even if it is valid. 
          state <= unpack;
        end
      end


      unpack:
      begin
        a_m <= {a[22 : 0], 3'd0};
        b_m <= {b[22 : 0], 3'd0};
        a_e <= a[30 : 23] - 127;
        b_e <= b[30 : 23] - 127;
        a_s <= a[31];
        b_s <= b[31];
        state <= special_cases;
      end

      special_cases:
      begin
        //if a is NaN or b is NaN return NaN 
        if ((a_e == 128 && a_m != 0) || (b_e == 128 && b_m != 0)) begin
          z[31] <= 1;
          z[30:23] <= 255;
          z[22] <= 1;
          z[21:0] <= 0;
          state <= put_z;
        //if a is inf return inf
        end else if (a_e == 128) begin
          z[31] <= a_s;
          z[30:23] <= 255;
          z[22:0] <= 0;
          //if a is inf and signs don't match return nan
          if ((b_e == 128) && (a_s != b_s)) begin
              z[31] <= b_s;
              z[30:23] <= 255;
              z[22] <= 1;
              z[21:0] <= 0;
          end
          state <= put_z;
        //if b is inf return inf
        end else if (b_e == 128) begin
          z[31] <= b_s;
          z[30:23] <= 255;
          z[22:0] <= 0;
          state <= put_z;
        //if a is zero return b
        end else if ((($signed(a_e) == -127) && (a_m == 0)) && (($signed(b_e) == -127) && (b_m == 0))) begin
          z[31] <= a_s & b_s;
          z[30:23] <= b_e[7:0] + 127;
          z[22:0] <= b_m[26:3];
          state <= put_z;
        //if a is zero return b
        end else if (($signed(a_e) == -127) && (a_m == 0)) begin
          z[31] <= b_s;
          z[30:23] <= b_e[7:0] + 127;
          z[22:0] <= b_m[26:3];
          state <= put_z;
        //if b is zero return a
        end else if (($signed(b_e) == -127) && (b_m == 0)) begin
          z[31] <= a_s;
          z[30:23] <= a_e[7:0] + 127;
          z[22:0] <= a_m[26:3];
          state <= put_z;
        end else begin
          //Denormalised Number
          if ($signed(a_e) == -127) begin
            a_e <= -126;
          end else begin
            a_m[26] <= 1;
          end
          //Denormalised Number
          if ($signed(b_e) == -127) begin
            b_e <= -126;
          end else begin
            b_m[26] <= 1;
          end
          state <= align;
        end
      end

      align:
      begin
        if ($signed(a_e) > $signed(b_e)) begin
          b_e <= b_e + 1;
          b_m <= b_m >> 1;
          b_m[0] <= b_m[0] | b_m[1];
        end else if ($signed(a_e) < $signed(b_e)) begin
          a_e <= a_e + 1;
          a_m <= a_m >> 1;
          a_m[0] <= a_m[0] | a_m[1];
        end else begin
          state <= add_0;
        end
      end

      add_0:
      begin
        z_e <= a_e;
        if (a_s == b_s) begin
          sum <= a_m + b_m;
          z_s <= a_s;
        end else begin
          if (a_m >= b_m) begin
            sum <= a_m - b_m;
            z_s <= a_s;
          end else begin
            sum <= b_m - a_m;
            z_s <= b_s;
          end
        end
        state <= add_1;
      end

      add_1:
      begin
        if (sum[27]) begin
          z_m <= sum[27:4];
          guard <= sum[3];
          round_bit <= sum[2];
          sticky <= sum[1] | sum[0];
          z_e <= z_e + 1;
        end else begin
          z_m <= sum[26:3];
          guard <= sum[2];
          round_bit <= sum[1];
          sticky <= sum[0];
        end
        state <= normalise_1;
      end

      normalise_1:
      begin
        if (z_m[23] == 0 && $signed(z_e) > -126) begin
          z_e <= z_e - 1;
          z_m <= z_m << 1;
          z_m[0] <= guard;
          guard <= round_bit;
          round_bit <= 0;
        end else begin
          state <= normalise_2;
        end
      end

      normalise_2:
      begin
        if ($signed(z_e) < -126) begin
          z_e <= z_e + 1;
          z_m <= z_m >> 1;
          guard <= z_m[0];
          round_bit <= guard;
          sticky <= sticky | round_bit;
        end else begin
          state <= round;
        end
      end

      round:
      begin
        if (guard && (round_bit | sticky | z_m[0])) begin
          z_m <= z_m + 1;
          if (z_m == 24'hffffff) begin
            z_e <=z_e + 1;
          end
        end
        state <= pack;
      end

      pack:
      begin
        z[22 : 0] <= z_m[22:0];
        z[30 : 23] <= z_e[7:0] + 127;
        z[31] <= z_s;
        if ($signed(z_e) == -126 && z_m[23] == 0) begin
          z[30 : 23] <= 0;
        end
        if ($signed(z_e) == -126 && z_m[23:0] == 24'h0) begin
          z[31] <= 1'b0; // FIX SIGN BUG: -a + a = +0.
        end
        //if overflow occurs, return inf
        if ($signed(z_e) > 127) begin
          z[22 : 0] <= 0;
          z[30 : 23] <= 255;
          z[31] <= z_s;
        end
        state <= put_z;
      end

      put_z: //Final state valid output is ready , make the output STB/VALID = 1, put valid output.
      begin
        adder_output_STB_reg <= 1;
        output_sum_reg <= z;
        if (adder_output_STB_reg && !(output_module_BUSY)) begin //Once output module is no more BUSY it lowers it's busy signal and output is then taken by next module.
          adder_output_STB_reg <= 0; //Output is no more valid.
          state <= get_a_and_b; //Go back to initial state.
        end
      end

    endcase

    if (rst == 1) begin //At Active high reset, module is no more BUSY, go to initial state and wait for valid inputs. Input is don't care and output is don't care , so output VALID/STB = 0.
      state <= get_a_and_b;
      adder_BUSY_reg <= 0; 
      adder_output_STB_reg <= 0;
    end

  end
  
  `ifdef SYNTHESIS_OFF //Purely combinational logic for debugging purpose, based on hexadecimal encoded states it will show named states in waveform //see this register in ASCII.
  reg [8*13:0] statename;//Highest 13 Number of ASCII letters each 8 bits.
  always@* begin
    case (1'b1)
      (state === get_a_and_b)  : statename = "GET_A_AND_B";
      (state === unpack)       : statename = "UNPACK";
      (state === special_cases): statename = "SPECIAL_CASES";//13 ASCII letters
      (state === align)        : statename = "ALIGN";
      (state === add_0)        : statename = "ADD_0";
      (state === add_1)        : statename = "ADD_1";
      (state === normalise_1)  : statename = "NORMALIZE_1";
      (state === normalise_2)  : statename = "NORMALIZE_2";
      (state === round)        : statename = "ROUND";
      (state === pack)         : statename = "PACK";
      (state === put_z)        : statename = "PUT_Z";
    endcase
  end//always
  `endif

  //Continuous assignments
  
  assign adder_BUSY = adder_BUSY_reg;
  assign adder_output_STB = adder_output_STB_reg;
  assign output_sum = output_sum_reg;

endmodule



/*////////////////////////////////////////1 Bit Full Adder////////////////////////////////////////////////////////////////
 
module full_adder 
  (
   clk_adder,
   i_bit1,
   i_bit2,
   i_carry,
   o_sum,
   o_carry
   );
  
  input  clk_adder;
  input  i_bit1;
  input  i_bit2;
  input  i_carry;
  output o_sum;
  output o_carry;

  wire   w_WIRE_1;
  wire   w_WIRE_2;
  wire   w_WIRE_3;
  
  wire o_sum_temp;
  wire o_carry_temp;
  
  reg o_sum_reg;
  reg o_carry_reg;
      
  assign w_WIRE_1 = i_bit1 ^ i_bit2;
  assign w_WIRE_2 = w_WIRE_1 & i_carry;
  assign w_WIRE_3 = i_bit1 & i_bit2;

  assign o_sum_temp   = w_WIRE_1 ^ i_carry;
  assign o_carry_temp = w_WIRE_2 | w_WIRE_3;
  
  //Pipeline
  always@(posedge clk_adder)begin
  o_sum_reg   <= o_sum_temp;
  o_carry_reg <= o_carry_temp;
  end

  assign o_sum   = o_sum_reg;
  assign o_carry = o_carry_reg;
  // FYI: Code above using wires will produce the same results as:
  // assign o_sum   = i_bit1 ^ i_bit2 ^ i_carry;
  // assign o_carry = (i_bit1 ^ i_bit2) & i_carry) | (i_bit1 & i_bit2);

  // Wires are just used to be explicit. 
  
endmodule // full_adder


////////////////////////////////////////Parameterized Unsigned Ripplecarry Adder//////////////////////////////////////////////////////////////// 
module ripple_carry_adder 
  #(parameter WIDTH=22)
  (
   input clk_adder,
   input [WIDTH-1:0] i_add_term1,
   input [WIDTH-1:0] i_add_term2,
   output [WIDTH:0]  o_result
   );
     
  wire [WIDTH:0]     w_CARRY;
  wire [WIDTH-1:0]   w_SUM;
   
  // No carry input on first full adder  
  assign w_CARRY[0] = 1'b0;        
   
  genvar             ii;
  generate 
    for (ii=0; ii<WIDTH; ii=ii+1) 
      begin
        full_adder full_adder_inst
            ( .clk_adder(clk_adder),
              .i_bit1(i_add_term1[ii]),
              .i_bit2(i_add_term2[ii]),
              .i_carry(w_CARRY[ii]),
              .o_sum(w_SUM[ii]),
              .o_carry(w_CARRY[ii+1])
              );
      end
  endgenerate
   
  assign o_result = {w_CARRY[WIDTH], w_SUM};   // Verilog Concatenation
 
endmodule // ripple_carry_adder
*/

fpu_adder/fpu_tb.sv
// Code your testbench here
// or browse Examples
module tb;
  reg [31:0] a, b;
  reg adder_input_STB;
  wire adder_BUSY;
  reg clk;
  reg rst;
  wire [31:0] output_sum;
  wire adder_output_STB;
  reg output_module_BUSY;
  
  reg transaction;
  assign transaction = (adder_input_STB && !(adder_BUSY));//Indicates when actually data is being taken by adder module
  
  adder adder_fpu_inst //adder instantiation
  (.input_a(a), 
   .input_b(b), 
   .adder_input_STB(adder_input_STB), 
   .adder_BUSY(adder_BUSY), 
   .clk(clk), 
   .rst(rst),
   .output_sum(output_sum),
   .adder_output_STB(adder_output_STB),
   .output_module_BUSY(output_module_BUSY)
  );
  
  always #5 clk = ~clk; //Clock generation
  
  initial begin
    $dumpfile("dump.vcd");//Signals are dumped in vcd starting at 0 time until $finish. 
    $dumpvars;//All variables are dumped both in tb and DUT.
    rst = 1; clk = 0; adder_input_STB = 0 ; output_module_BUSY = 0; //First reset is given output should be in don't care condition, clock is initialized to 0 and BUSY signal of output module connected to adder is driven low, i.e., output module is always ready to accept data whenever valid data comes to it.
    #10;
    rst = 0; //After some delay reset is turned low and STB is made high and valid operands are given. These operands are taken by adder just in the next clock since BUSY was low. 
    adder_input_STB = 1 ; 
    a = 'h40000000;//2
    b = 'h40400000;//3
    #10; //After some delay STB is high already and valid operands are given. But these operands are taken after several clock cycles later because BUSY is now high.So transaction only takes place when STB=1 and BUSY = 0 indicated by the transaction signal several clock cycles later i.e., after the current one is finished. 
    a = 'h40800000;//4
    b = 'h40a00000;//5
    #150;
    adder_input_STB = 0 ; //After several clocks STB is made low since no more valid operands to give to adder for further processing.
    //#20;
    #250;
    $finish; //Simulation is stopped after some more clock cycles.
  end
  
  initial begin
    $monitor("Time-%t, input_a-%h, input_b-%h, output_sum-%h", $time, a, b, output_sum);//Monitor these signals anytime any of them change starting from 0 time.
  end
endmodule

fpu_adder/dump.vcd
$date
	Fri Nov 13 06:20:25 2020
$end
$version
	QuestaSim Version 2020.1_1
$end
$timescale
	1ns
$end

$scope module tb $end
$var reg 32 ! a [31:0] $end
$var reg 32 " b [31:0] $end
$var reg 1 # adder_input_STB $end
$var wire 1 $ adder_BUSY $end
$var reg 1 % clk $end
$var reg 1 & rst $end
$var wire 1 ' output_sum [31] $end
$var wire 1 ( output_sum [30] $end
$var wire 1 ) output_sum [29] $end
$var wire 1 * output_sum [28] $end
$var wire 1 + output_sum [27] $end
$var wire 1 , output_sum [26] $end
$var wire 1 - output_sum [25] $end
$var wire 1 . output_sum [24] $end
$var wire 1 / output_sum [23] $end
$var wire 1 0 output_sum [22] $end
$var wire 1 1 output_sum [21] $end
$var wire 1 2 output_sum [20] $end
$var wire 1 3 output_sum [19] $end
$var wire 1 4 output_sum [18] $end
$var wire 1 5 output_sum [17] $end
$var wire 1 6 output_sum [16] $end
$var wire 1 7 output_sum [15] $end
$var wire 1 8 output_sum [14] $end
$var wire 1 9 output_sum [13] $end
$var wire 1 : output_sum [12] $end
$var wire 1 ; output_sum [11] $end
$var wire 1 < output_sum [10] $end
$var wire 1 = output_sum [9] $end
$var wire 1 > output_sum [8] $end
$var wire 1 ? output_sum [7] $end
$var wire 1 @ output_sum [6] $end
$var wire 1 A output_sum [5] $end
$var wire 1 B output_sum [4] $end
$var wire 1 C output_sum [3] $end
$var wire 1 D output_sum [2] $end
$var wire 1 E output_sum [1] $end
$var wire 1 F output_sum [0] $end
$var wire 1 G adder_output_STB $end
$var reg 1 H output_module_BUSY $end
$var reg 1 I transaction $end

$scope module adder_fpu_inst $end
$var parameter 4 J get_a_and_b $end
$var parameter 4 K unpack $end
$var parameter 4 L special_cases $end
$var parameter 4 M align $end
$var parameter 4 N add_0 $end
$var parameter 4 O add_1 $end
$var parameter 4 P normalise_1 $end
$var parameter 4 Q normalise_2 $end
$var parameter 4 R round $end
$var parameter 4 S pack $end
$var parameter 4 T put_z $end
$var wire 1 U clk $end
$var wire 1 V rst $end
$var wire 1 W input_a [31] $end
$var wire 1 X input_a [30] $end
$var wire 1 Y input_a [29] $end
$var wire 1 Z input_a [28] $end
$var wire 1 [ input_a [27] $end
$var wire 1 \ input_a [26] $end
$var wire 1 ] input_a [25] $end
$var wire 1 ^ input_a [24] $end
$var wire 1 _ input_a [23] $end
$var wire 1 ` input_a [22] $end
$var wire 1 a input_a [21] $end
$var wire 1 b input_a [20] $end
$var wire 1 c input_a [19] $end
$var wire 1 d input_a [18] $end
$var wire 1 e input_a [17] $end
$var wire 1 f input_a [16] $end
$var wire 1 g input_a [15] $end
$var wire 1 h input_a [14] $end
$var wire 1 i input_a [13] $end
$var wire 1 j input_a [12] $end
$var wire 1 k input_a [11] $end
$var wire 1 l input_a [10] $end
$var wire 1 m input_a [9] $end
$var wire 1 n input_a [8] $end
$var wire 1 o input_a [7] $end
$var wire 1 p input_a [6] $end
$var wire 1 q input_a [5] $end
$var wire 1 r input_a [4] $end
$var wire 1 s input_a [3] $end
$var wire 1 t input_a [2] $end
$var wire 1 u input_a [1] $end
$var wire 1 v input_a [0] $end
$var wire 1 w input_b [31] $end
$var wire 1 x input_b [30] $end
$var wire 1 y input_b [29] $end
$var wire 1 z input_b [28] $end
$var wire 1 { input_b [27] $end
$var wire 1 | input_b [26] $end
$var wire 1 } input_b [25] $end
$var wire 1 ~ input_b [24] $end
$var wire 1 !! input_b [23] $end
$var wire 1 "! input_b [22] $end
$var wire 1 #! input_b [21] $end
$var wire 1 $! input_b [20] $end
$var wire 1 %! input_b [19] $end
$var wire 1 &! input_b [18] $end
$var wire 1 '! input_b [17] $end
$var wire 1 (! input_b [16] $end
$var wire 1 )! input_b [15] $end
$var wire 1 *! input_b [14] $end
$var wire 1 +! input_b [13] $end
$var wire 1 ,! input_b [12] $end
$var wire 1 -! input_b [11] $end
$var wire 1 .! input_b [10] $end
$var wire 1 /! input_b [9] $end
$var wire 1 0! input_b [8] $end
$var wire 1 1! input_b [7] $end
$var wire 1 2! input_b [6] $end
$var wire 1 3! input_b [5] $end
$var wire 1 4! input_b [4] $end
$var wire 1 5! input_b [3] $end
$var wire 1 6! input_b [2] $end
$var wire 1 7! input_b [1] $end
$var wire 1 8! input_b [0] $end
$var wire 1 9! adder_input_STB $end
$var wire 1 $ adder_BUSY $end
$var wire 1 ' output_sum [31] $end
$var wire 1 ( output_sum [30] $end
$var wire 1 ) output_sum [29] $end
$var wire 1 * output_sum [28] $end
$var wire 1 + output_sum [27] $end
$var wire 1 , output_sum [26] $end
$var wire 1 - output_sum [25] $end
$var wire 1 . output_sum [24] $end
$var wire 1 / output_sum [23] $end
$var wire 1 0 output_sum [22] $end
$var wire 1 1 output_sum [21] $end
$var wire 1 2 output_sum [20] $end
$var wire 1 3 output_sum [19] $end
$var wire 1 4 output_sum [18] $end
$var wire 1 5 output_sum [17] $end
$var wire 1 6 output_sum [16] $end
$var wire 1 7 output_sum [15] $end
$var wire 1 8 output_sum [14] $end
$var wire 1 9 output_sum [13] $end
$var wire 1 : output_sum [12] $end
$var wire 1 ; output_sum [11] $end
$var wire 1 < output_sum [10] $end
$var wire 1 = output_sum [9] $end
$var wire 1 > output_sum [8] $end
$var wire 1 ? output_sum [7] $end
$var wire 1 @ output_sum [6] $end
$var wire 1 A output_sum [5] $end
$var wire 1 B output_sum [4] $end
$var wire 1 C output_sum [3] $end
$var wire 1 D output_sum [2] $end
$var wire 1 E output_sum [1] $end
$var wire 1 F output_sum [0] $end
$var wire 1 G adder_output_STB $end
$var wire 1 :! output_module_BUSY $end
$var reg 1 ;! adder_output_STB_reg $end
$var reg 32 <! output_sum_reg [31:0] $end
$var reg 1 =! adder_BUSY_reg $end
$var reg 4 >! state [3:0] $end
$var reg 32 ?! a [31:0] $end
$var reg 32 @! b [31:0] $end
$var reg 32 A! z [31:0] $end
$var reg 27 B! a_m [26:0] $end
$var reg 27 C! b_m [26:0] $end
$var reg 24 D! z_m [23:0] $end
$var reg 10 E! a_e [9:0] $end
$var reg 10 F! b_e [9:0] $end
$var reg 10 G! z_e [9:0] $end
$var reg 1 H! a_s $end
$var reg 1 I! b_s $end
$var reg 1 J! z_s $end
$var reg 1 K! guard $end
$var reg 1 L! round_bit $end
$var reg 1 M! sticky $end
$var reg 28 N! sum [27:0] $end
$var reg 105 O! statename [104:0] $end
$upscope $end
$upscope $end

$scope begin std $end
$upscope $end
$enddefinitions $end
#0
$dumpvars
bx !
bx "
0#
0%
1&
0H
0I
x;!
bx <!
x=!
bx >!
bx ?!
bx @!
bx A!
bx B!
bx C!
bx D!
bx E!
bx F!
bx G!
xH!
xI!
xJ!
xK!
xL!
xM!
bx N!
bx O!
b0 J
b1 K
b10 L
b11 M
b100 N
b101 O
b110 P
b111 Q
b1000 R
b1001 S
b1010 T
x$
xF
xE
xD
xC
xB
xA
x@
x?
x>
x=
x<
x;
x:
x9
x8
x7
x6
x5
x4
x3
x2
x1
x0
x/
x.
x-
x,
x+
x*
x)
x(
x'
xG
0:!
1V
0U
09!
x8!
x7!
x6!
x5!
x4!
x3!
x2!
x1!
x0!
x/!
x.!
x-!
x,!
x+!
x*!
x)!
x(!
x'!
x&!
x%!
x$!
x#!
x"!
x!!
x~
x}
x|
x{
xz
xy
xx
xw
xv
xu
xt
xs
xr
xq
xp
xo
xn
xm
xl
xk
xj
xi
xh
xg
xf
xe
xd
xc
xb
xa
x`
x_
x^
x]
x\
x[
xZ
xY
xX
xW
$end
#5
1%
1U
b0 >!
0=!
0;!
0$
0G
b100011101000101010101000101111101000001010111110100000101001110010001000101111101000010 O!
#10
0&
1#
b1000000000000000000000000000000 !
b1000000010000000000000000000000 "
0%
1I
0V
19!
08!
07!
06!
05!
04!
03!
02!
01!
00!
0/!
0.!
0-!
0,!
0+!
0*!
0)!
0(!
0'!
0&!
0%!
0$!
0#!
1"!
0!!
0~
0}
0|
0{
0z
0y
1x
0w
0v
0u
0t
0s
0r
0q
0p
0o
0n
0m
0l
0k
0j
0i
0h
0g
0f
0e
0d
0c
0b
0a
0`
0_
0^
0]
0\
0[
0Z
0Y
1X
0W
0U
#15
1%
1U
b1000000000000000000000000000000 ?!
b1000000010000000000000000000000 @!
1=!
b1 >!
1$
0I
b10101010100111001010000010000010100001101001011 O!
#20
b1000000100000000000000000000000 !
b1000000101000000000000000000000 "
0%
1#!
0"!
1!!
1_
0U
#25
1%
1U
b0 B!
b10000000000000000000000000 C!
b1 E!
b1 F!
0H!
0I!
b10 >!
b1010011010100000100010101000011010010010100000101001100010111110100001101000001010100110100010101010011 O!
#30
0%
0U
#35
1%
1U
b100000000000000000000000000 B!
b110000000000000000000000000 C!
b11 >!
b100000101001100010010010100011101001110 O!
#40
0%
0U
#45
1%
1U
b100 >!
b100000101000100010001000101111100110000 O!
#50
0%
0U
#55
1%
1U
b1 G!
b1010000000000000000000000000 N!
0J!
b101 >!
b100000101000100010001000101111100110001 O!
#60
0%
0U
#65
1%
1U
b101000000000000000000000 D!
0K!
0L!
0M!
b10 G!
b110 >!
b100111001001111010100100100110101000001010011000100100101011010010001010101111100110001 O!
#70
0%
0U
#75
1%
1U
b111 >!
b100111001001111010100100100110101000001010011000100100101011010010001010101111100110010 O!
#80
0%
0U
#85
1%
1U
b1000 >!
b101001001001111010101010100111001000100 O!
#90
0%
0U
#95
1%
1U
b1001 >!
b1010000010000010100001101001011 O!
#100
0%
0U
#105
1%
1U
bx01000000000000000000000 A!
bx1000000101000000000000000000000 A!
b1000000101000000000000000000000 A!
b1010 >!
b101000001010101010101000101111101011010 O!
#110
0%
0U
#115
1%
1U
1;!
b1000000101000000000000000000000 <!
1G
0F
0E
0D
0C
0B
0A
0@
0?
0>
0=
0<
0;
0:
09
08
07
06
05
04
03
02
11
00
1/
0.
0-
0,
0+
0*
0)
1(
0'
#120
0%
0U
#125
1%
1U
0;!
b0 >!
0G
b100011101000101010101000101111101000001010111110100000101001110010001000101111101000010 O!
#130
0%
0U
#135
1%
1U
0=!
0$
1I
#140
0%
0U
#145
1%
1U
b1000000100000000000000000000000 ?!
b1000000101000000000000000000000 @!
1=!
b1 >!
1$
0I
b10101010100111001010000010000010100001101001011 O!
#150
0%
0U
#155
1%
1U
b0 B!
b1000000000000000000000000 C!
b10 E!
b10 F!
b10 >!
b1010011010100000100010101000011010010010100000101001100010111110100001101000001010100110100010101010011 O!
#160
0%
0U
#165
1%
1U
b100000000000000000000000000 B!
b101000000000000000000000000 C!
b11 >!
b100000101001100010010010100011101001110 O!
#170
0#
0%
09!
0U
#175
1%
1U
b100 >!
b100000101000100010001000101111100110000 O!
#180
0%
0U
#185
1%
1U
b1001000000000000000000000000 N!
b101 >!
b100000101000100010001000101111100110001 O!
#190
0%
0U
#195
1%
1U
b100100000000000000000000 D!
b11 G!
b110 >!
b100111001001111010100100100110101000001010011000100100101011010010001010101111100110001 O!
#200
0%
0U
#205
1%
1U
b111 >!
b100111001001111010100100100110101000001010011000100100101011010010001010101111100110010 O!
#210
0%
0U
#215
1%
1U
b1000 >!
b101001001001111010101010100111001000100 O!
#220
0%
0U
#225
1%
1U
b1001 >!
b1010000010000010100001101001011 O!
#230
0%
0U
#235
1%
1U
b1000000100100000000000000000000 A!
b1000001000100000000000000000000 A!
b1010 >!
b101000001010101010101000101111101011010 O!
#240
0%
0U
#245
1%
1U
1;!
b1000001000100000000000000000000 <!
1G
12
01
0/
1.
#250
0%
0U
#255
1%
1U
0;!
b0 >!
0G
b100011101000101010101000101111101000001010111110100000101001110010001000101111101000010 O!
#260
0%
0U
#265
1%
1U
0=!
0$
